HydroGenerate/__init__.py
HydroGenerate/flow_preprocessing.py
HydroGenerate/hydraulic_processing.py
HydroGenerate/hydropower_potential.py
HydroGenerate/turbine_calculation.py
tests/__init__.py
HydroGenerate-1.3.0.dist-info/LICENSE
HydroGenerate-1.3.0.dist-info/METADATA
HydroGenerate-1.3.0.dist-info/NOTICE.txt
HydroGenerate-1.3.0.dist-info/WHEEL
HydroGenerate-1.3.0.dist-info/top_level.txt
HydroGenerate-1.3.0.dist-info/RECORD
