Metadata-Version: 2.1
Name: HydroGenerate
Version: 1.3.0
Summary: HydroGenerate is an open-source python library that has the capability of estimating hydropower generation based on flow and head.
Home-page: https://github.com/IdahoLabResearch/HydroGenerate
Author: Bhaskar Mitra, Shiloh Elliot
Author-email: Juan Gallego-Calderon <juan.gallegocalderon@inl.gov>, Camilo Bastidas-Pacheco <camilojose.bastidaspacheco@inl.gov>, Soumyadeep Nag <soumyadeep.nag@inl.gov>, Thomas Mosier <thomas.mosier@inl.gov>
Maintainer-email: Juan Gallego-Calderon <juan.gallegocalderon@inl.gov>, Camilo Bastidas-Pacheco <camilojose.bastidaspacheco@inl.gov>
Project-URL: Homepage, https://idaholabresearch.github.io/HydroGenerate/
Project-URL: Documentation, https://idaholabresearch.github.io/HydroGenerate/
Project-URL: Repository, https://github.com/IdahoLabResearch/HydroGenerate
Project-URL: Bug Tracker, https://github.com/IdahoLabResearch/HydroGenerate
Keywords: hydropower,hydrokinetic,potential
Classifier: Development Status :: 4 - Beta
Classifier: Programming Language :: Python :: 3
Requires-Python: >=3.8
License-File: LICENSE
License-File: NOTICE.txt
Requires-Dist: requests
Requires-Dist: numpy
Requires-Dist: pandas
Requires-Dist: scipy
Requires-Dist: matplotlib
Requires-Dist: shapely
